gstreamer_gtk-1.27.90.data/purelib/gstreamer_gtk/__init__.py
gstreamer_gtk-1.27.90.data/purelib/gstreamer_gtk/bin/accesskit-c-0.17.dll
gstreamer_gtk-1.27.90.data/purelib/gstreamer_gtk/bin/epoxy-0.dll
gstreamer_gtk-1.27.90.data/purelib/gstreamer_gtk/bin/gtk-4-1.dll
gstreamer_gtk-1.27.90.data/purelib/gstreamer_gtk/lib/girepository-1.0/Gdk-4.0.typelib
gstreamer_gtk-1.27.90.data/purelib/gstreamer_gtk/lib/girepository-1.0/GdkWin32-4.0.typelib
gstreamer_gtk-1.27.90.data/purelib/gstreamer_gtk/lib/girepository-1.0/Graphene-1.0.typelib
gstreamer_gtk-1.27.90.data/purelib/gstreamer_gtk/lib/girepository-1.0/Gsk-4.0.typelib
gstreamer_gtk-1.27.90.data/purelib/gstreamer_gtk/lib/girepository-1.0/Gtk-4.0.typelib
gstreamer_gtk-1.27.90.data/purelib/gstreamer_gtk/lib/gstreamer-1.0/gstgtk4.dll
gstreamer_gtk-1.27.90.dist-info/METADATA
gstreamer_gtk-1.27.90.dist-info/WHEEL
gstreamer_gtk-1.27.90.dist-info/top_level.txt
gstreamer_gtk-1.27.90.dist-info/RECORD
